wcf_http/__init__.py
wcf_http/assets/images/wcf-http.ico
wcf_http/assets/images/wcf-http.png
wcf_http/core.py
wcf_http/main.py
wcf_http/preamble.py
wcf_http_server-39.2.4.1.15.dist-info/entry_points.txt
wcf_http_server-39.2.4.1.15.dist-info/METADATA
wcf_http_server-39.2.4.1.15.dist-info/WHEEL
wcf_http_server-39.2.4.1.15.dist-info/RECORD
