Metadata-Version: 2.1
Name: wcf-http-server
Version: 39.2.4.1.15
Summary: 一个玩微信的工具
Author: sean
Author-email: sean.li@vectorindex.cloud
Requires-Python: >=3.10,<4.0
Classifier: Programming Language :: Python :: 3
Classifier: Programming Language :: Python :: 3.10
Classifier: Programming Language :: Python :: 3.11
Classifier: Programming Language :: Python :: 3.12
Provides-Extra: systray
Requires-Dist: fastapi (>=0.103.2,<0.104.0)
Requires-Dist: pillow (>=11.0.0,<12.0.0) ; extra == "systray"
Requires-Dist: pystray (>=0.19.5,<0.20.0) ; extra == "systray"
Requires-Dist: uvicorn (>=0.23.2,<0.24.0)
Requires-Dist: wcferry (>=39.2.4,<39.3.0)
